dependency_collector/__init__.py
dependency_collector/cli.py
dependency_collector-0.1.0.dist-info/METADATA
dependency_collector-0.1.0.dist-info/WHEEL
dependency_collector-0.1.0.dist-info/entry_points.txt
dependency_collector-0.1.0.dist-info/RECORD
