Metadata-Version: 2.4
Name: dependency-collector
Version: 0.1.0
Summary: Python software for local retrieval of project dependencies.
Author-email: Simon Delmas <delmas.simon@gmail.com>
Requires-Python: >=3.13
Requires-Dist: artifacts-keyring>=0.4.0
Requires-Dist: click>=8.1.8
Requires-Dist: keyring>=25.6.0
Requires-Dist: pip>=24.3.1
